{
  "url": "https://akhbarelyom.com/news/newssection/1/1/%D8%A3%D8%AE%D8%A8%D8%A7%D8%B1-%D9%85%D8%B5%D8%B1",
  "title": "أخبار مصر| بوابة أخبار اليوم الإلكترونية",
  "content": "الرئيسية مصر أخبار مصر محافظات سياحة وسفر عربي ودولي عرب عالم أفريقيا أخبار اليوم أوتو برلمان اليوم اقتصاد بنوك وشركات عقارات طاقة أخبار الرياضة أخبار الحوادث فن وثقافة منوعات حكايات كلاسيك المرأة والطفل اخبار مديكال مجتمع كاريكاتير علوم وتكنولوجيا اتصالات الفضاء سلاح العاب وتطبيقات المزيد تحقيقات T.Vاخبار اليوم توك شو إنفوجراف أخبار الصين في خدمتك عاجل ارتفاع سعر الدولار أمام الجنيه بداية تعاملات الأربعاء 1 ابريل 2026 «أمطار ورياح».. «الأرصاد» تكشف تفاصيل حالة عدم الاستقرار في الأحوال الجوية القابضة للمياه: رفع درجة الاستعداد القصوى لمواجهة موجة الطقس غير المستقر أخبار فاتتك وأنت نائم| الاحتلال يستهدف قيادي بارز في حزب الله.. و«ترامب» يعلن خطة الانسحاب من إيران إلغاء رحلات البالون في الأقصر بسبب سوء الأحوال الجوية ارتفاع أسعار الذهب عالميًا في بداية تعاملات الأربعاء الجيش الإسرائيلي: رصد إطلاق صاروخ من اليمن رئيس جامعة العريش: مبادرات وبرامج مشتركة لدعم الأنشطة الرياضية حملة رقابية على الأسواق والمحلات التجارية بالعريش حركة القطارات| 45 دقيقة تأخيرًا بين قليوب والزقازيق والمنصورة.. الأربعاء 1 أبريل بحث أخبار مصر حركة القطارات| 45 دقيقة تأخيرًا بين قليوب والزقازيق والمنصورة.. الأربعاء 1 أبريل حركة القطارات| 90 دقيقة متوسط تأخيرات «بنها وبورسعيد».. الأربعاء 1 أبريل 60 دقيقة متوسط تأخيرات قطارات الصعيد.. الأربعاء 1 أبريل 45 دقيقة متوسط تأخيرات قطارات «طنطا - دمياط».. الأربعاء 1 أبريل 30 دقيقة تأخرًا في حركة قطارات «القاهرة - الإسكندرية».. الأربعاء 1 أبريل بسبب سوء الطقس.. إجازة في المعاهد الأزهرية الأربعاء أمطار رعدية ورياح مثيرة للأتربة.. الأرصاد تحذر من طقس اليوم الأربعاء الأرصاد: غطاء سحابي ممطر يغطي الصحراء الغربية وغرب البلاد ويتجه نحو القاهرة نشرة منتصف الليل| إجازة للمدارس وحريق الزيتون وتعادل مثير للفراعنة أمام إسبانيا طلاب «إعلام القاهرة» يطلقون فعالية «UV Alert» للتوعية بمخاطر الأشعة فوق البنفسجية أدعية مستحبة وقت المطر.. تعرف عليها إياتا: ارتفاع الطلب العالمي على السفر الجوي 6.1% في فبراير مصرع وإصابة 5 أشخاص.. السيطرة على حريق مصنع ملابس بحي الزيتون «التعليم» تنسق مع «الأرصاد» لحسم مصير الدراسة بعد غدٍ الخميس محكمة النقض والمحاكم الاستئنافية تُطبق إجراءات ترشيد الإنفاق والاستهلاك محافظ القاهرة يتفقد موقع حريق مصنع ملابس بحي الزيتون برلمانية: دعوة الرئيس السيسي لوقف الحرب رؤية استباقية تنذر بحجم التداعيات بسبب الطقس السيء.. تأجيل امتحانات المعاهد الأزهرية مجلس الوزراء يعلن تعليق قرارات الإغلاق خلال أعياد الإخوة الأقباط سقوط أمطار على مناطق متفرقة بالقاهرة محافظ القاهرة: تطبيق نظام العمل أونلاين بديوان عام المحافظة التعليم العالي تعلن استمرار الدراسة بالجامعات والمعاهد غدا الأربعاء لا يوجد المزيد من البيانات. 0 © الحقوق محفوظة لمؤسسة أخبار اليوم 1944 - 2024 اتصل بنا من نحن سياسة الخصوصية للإعلان",
  "word_count": 400,
  "method": "http_simple",
  "collected_at": "2026-04-01T08:02:43.992347+00:00"
}